GeoFaker/Func.py
GeoFaker/__init__.py
GeoFaker/data/usa.json
geofaker-1.1.dist-info/LICENSE
geofaker-1.1.dist-info/METADATA
geofaker-1.1.dist-info/WHEEL
geofaker-1.1.dist-info/top_level.txt
geofaker-1.1.dist-info/RECORD
